{
  "id": "0263ba3a1cdd15cb",
  "fields": {
    "apply_url": "https://jobs.ashbyhq.com/m-kopa/108edbb0-cc89-42b3-b81c-cf68907776cb/application",
    "company": "M-Kopa",
    "compensation": "",
    "content_hash": "0263ba3a1cdd15cb",
    "department": "Smartphones",
    "description": "[https://app.ashbyhq.com/api/images/user-content/1d985516-2a99-43c0-b591-957f5adaceb9/5ac97b31-49cd-4012-8bb0-5caf15e33c69/B25.png]\n\n\nWAREHOUSE OPERATIONS INTERN — M-KOPA GHANA\n\n[https://app.ashbyhq.com/api/images/user-content/1d985516-2a99-43c0-b591-957f5adaceb9/297722fd-050c-480e-b253-9d4e08fd0a0e/image.png]\n\nEvery smartphone that reaches an M-KOPA customer starts somewhere. It arrives in a warehouse, gets configured to spec, quality-checked, logged, and dispatched — before it ends up in the hands of someone who's using it to run a business, stay connected, or access financial services for the very first time. That process sounds simple. Done well, at volume, day after day, it's anything but.\n\nIf you're looking for an opportunity where you can learn by doing, build strong work habits, and be part of a team that keeps things moving behind the scenes — this is worth your attention.\n\nM-KOPA is looking for a Warehouse Operations Intern to join our Logistics and Warehouse Operations team. This is a junior, entry-level role designed for individuals who are early in their working journey — whether you've just finished school or have some exposure to a similar environment and want to build practical experience.\n\nThis is a hands-on, operational role at the heart of our supply chain — and it's the kind of opportunity that gives you real insight into how a fast-growing business runs on a day-to-day basis.\n\n[https://app.ashbyhq.com/api/images/user-content/1d985516-2a99-43c0-b591-957f5adaceb9/a3c6b36d-90ce-4933-a4a8-629fcb0beb24/image.png]\n\n\nWHAT M-KOPA IS BUILDING\n\nWe've served more than 7 million customers across Africa, unlocking over $2 billion in credit. 55% of those customers are accessing formal financial services for the very first time. 86% report a meaningful improvement in their quality of life. We're growing toward 10 million customers — and every device that flows through our warehouse is a step in that direction.\n\nOur product portfolio includes smartphones, digital loans, device protection, health insurance, and mobile data. The warehouse operation that supports all of this isn't a background function. It's the link between what we offer and what our customers actually receive.\n\n[https://app.ashbyhq.com/api/images/user-content/1d985516-2a99-43c0-b591-957f5adaceb9/d3418126-559b-4260-b294-f18de92c6dde/image.png]\n\n\nWHAT THE WORK ACTUALLY LOOKS LIKE\n\nYour primary focus will be setting up PAYGO phones accurately and efficiently — following approved steps and processes to ensure every device is ready before it reaches the sales team. The daily target is 300 units prepared for sale. This requires focus, consistency, and attention to detail, and it's where you'll build strong operational discipline.\n\nBeyond device setup, you'll support order processing and dispatch activities, helping to ensure the right stock reaches the right place at the right time. You'll assist with maintaining accurate stock records — tracking Current Stock, Stock in Channel, and Total Sales — and monitor devices using M-KOPA's internal systems.\n\nYou'll also help compile production data and support basic operational reporting so the wider team can understand how the warehouse is performing.\n\nKeeping your workstation clean, following 6S housekeeping standards, and adhering to safety, health, and environmental protocols are part of the role from day one. Proper use of PPE, taking care of company equipment, and working safely with your team are all essential.\n\nThis role involves structured, process-driven tasks that require consistency and reliability — and it’s a great environment to build discipline, teamwork, and a strong work ethic.\n\n[https://app.ashbyhq.com/api/images/user-content/1d985516-2a99-43c0-b591-957f5adaceb9/a24fc8af-b976-45f9-896e-837217ef068b/image.png]\n\n\nWHAT MAKES YOU READY FOR THIS\n\n - You’ve recently completed school (Matric) or have some early work experience, ideally in a warehouse, retail, or similar hands-on environment\n\n - You’re willing to learn, take direction, and build practical skills in a structured working environment\n\n - You have good attention to detail and can follow processes accurately, especially when working on tasks that require consistency and focus\n\n - You’re comfortable using basic computer systems or are open to learning\n\n - You’re dependable, take responsibility for your work, and work well as part of a team\n\n\nWHAT YOU'LL TAKE AWAY\n\nThis role is about building a strong foundation.\n\nYou'll gain practical exposure to how a warehouse operates in a fast-paced business. You'll understand how stock management connects to sales performance. You'll learn the importance of accuracy, consistency, and teamwork in an operational environment.\n\nMost importantly, you'll develop workplace habits and experience that can open doors into logistics, supply chain, retail operations, or broader business roles over time.\n\nIf you're starting out and looking for an opportunity to gain real experience, learn valuable skills, and be part of something meaningful — this is a strong place to begin.\n\nReady to be part of the operation that puts M-KOPA's products into customers' hands? Let's talk.\n\n[https://app.ashbyhq.com/api/images/user-content/1d985516-2a99-43c0-b591-957f5adaceb9/edfd1808-62ac-4f75-b330-bd3b893d88bf/image.png]\n\n\nWHY M-KOPA?\n\nAt M-KOPA, we empower our people to own their careers through diverse development programs, coaching partnerships, and on-the-job training. We support individual journeys with family-friendly policies, prioritize well-being, and embrace flexibility.\n\nJoin us in shaping the future of M-KOPA as we grow together. Explore more at m-kopa.com http://m-kopa.com.\n\n[https://app.ashbyhq.com/api/images/user-content/1d985516-2a99-43c0-b591-957f5adaceb9/369018b8-cf9c-49c7-95f1-1d414482ba57/B13.png]\n\nRecognized four times by the Financial Times as one Africa's fastest growing companies (2022, 2023, 2024 and 2025) and by TIME100 Most influential companies in the world 2023 and 2024 , we've served over 6 million customers, unlocking $1.5 billion in cumulative credit for the unbanked across Africa.\n\n[https://app.ashbyhq.com/api/images/user-content/1d985516-2a99-43c0-b591-957f5adaceb9/481f6724-8375-4f39-b514-fbe00b8fc3b5/B13.png]\n\nImportant Notice\n\nM-KOPA is an equal opportunity and affirmative action employer committed to assembling a diverse, broadly trained staff. Women, minorities, and people with disabilities are strongly encouraged to apply.\n\nM-KOPA explicitly prohibits the use of Forced or Child Labour and respects the rights of its employees to agree to terms and conditions of employment voluntarily, without coercion, and freely terminate their employment on appropriate notice. M-KOPA shall ensure that its Employees are of legal working age and shall comply with local laws for youth employment or student work, such as internships or apprenticeships. \n\nM-KOPA does not collect/charge any money as a pre-employment or post-employment requirement. This means that we never ask for ‘recruitment fees’, ‘processing fees’, ‘interview fees’, or any other kind of money in exchange for offer letters or interviews at any time during the hiring process.\n\nApplications for this position will be reviewed on a rolling basis. Shortlisting and interviews will take place at any stage during the recruitment process. We reserve the right to close the vacancy early if a suitable candidate is selected before the advertised closing date.\n\nIf your application is successful M-KOPA undertakes pre-employment background checks as part of its recruitment process, these include; criminal records, identification verification, academic qualifications, employment dates and employer references.",
    "employment_type": "FullTime",
    "is_active": true,
    "job_id": "0263ba3a1cdd15cb",
    "job_url": "https://jobs.ashbyhq.com/m-kopa/108edbb0-cc89-42b3-b81c-cf68907776cb",
    "location": "Ghana",
    "published_at": "2026-04-07T19:40:55Z",
    "remote": false,
    "scraped_at": "2026-04-12T12:16:45+05:30",
    "status": "new",
    "team": "Warehouse and Logistics",
    "title": "Warehouse Operations Assistant"
  },
  "vectors": {
    "embedding": [
      0,
      0,
      0,
      0,
      0,
      0,
      0,
      0,
      0,
      0,
      0,
      0,
      0,
      0,
      0,
      0,
      0,
      0,
      0,
      0,
      0,
      0,
      0,
      0,
      0,
      0,
      0,
      0,
      0,
      0,
      0,
      0,
      0,
      0,
      0,
      0,
      0,
      0,
      0,
      0,
      0,
      0,
      0,
      0,
      0,
      0,
      0,
      0,
      0,
      0,
      0,
      0,
      0,
      0,
      0,
      0,
      0,
      0,
      0,
      0,
      0,
      0,
      0,
      0,
      0,
      0,
      0,
      0,
      0,
      0,
      0,
      0,
      0,
      0,
      0,
      0,
      0,
      0,
      0,
      0,
      0,
      0,
      0,
      0,
      0,
      0,
      0,
      0,
      0,
      0,
      0,
      0,
      0,
      0,
      0,
      0,
      0,
      0,
      0,
      0,
      0,
      0,
      0,
      0,
      0,
      0,
      0,
      0,
      0,
      0,
      0,
      0,
      0,
      0,
      0,
      0,
      0,
      0,
      0,
      0,
      0,
      0,
      0,
      0,
      0,
      0,
      0,
      0,
      0,
      0,
      0,
      0,
      0,
      0,
      0,
      0,
      0,
      0,
      0,
      0,
      0,
      0,
      0,
      0,
      0,
      0,
      0,
      0,
      0,
      0,
      0,
      0,
      0,
      0,
      0,
      0,
      0,
      0,
      0,
      0,
      0,
      0,
      0,
      0,
      0,
      0,
      0,
      0,
      0,
      0,
      0,
      0,
      0,
      0,
      0,
      0,
      0,
      0,
      0,
      0,
      0,
      0,
      0,
      0,
      0,
      0,
      0,
      0,
      0,
      0,
      0,
      0,
      0,
      0,
      0,
      0,
      0,
      0,
      0,
      0,
      0,
      0,
      0,
      0,
      0,
      0,
      0,
      0,
      0,
      0,
      0,
      0,
      0,
      0,
      0,
      0,
      0,
      0,
      0,
      0,
      0,
      0,
      0,
      0,
      0,
      0,
      0,
      0,
      0,
      0,
      0,
      0,
      0,
      0,
      0,
      0,
      0,
      0,
      0,
      0,
      0,
      0,
      0,
      0,
      0,
      0,
      0,
      0,
      0,
      0,
      0,
      0,
      0,
      0,
      0,
      0,
      0,
      0,
      0,
      0,
      0,
      0,
      0,
      0,
      0,
      0,
      0,
      0,
      0,
      0,
      0,
      0,
      0,
      0,
      0,
      0,
      0,
      0,
      0,
      0,
      0,
      0,
      0,
      0,
      0,
      0,
      0,
      0,
      0,
      0,
      0,
      0,
      0,
      0,
      0,
      0,
      0,
      0,
      0,
      0,
      0,
      0,
      0,
      0,
      0,
      0,
      0,
      0,
      0,
      0,
      0,
      0,
      0,
      0,
      0,
      0,
      0,
      0,
      0,
      0,
      0,
      0,
      0,
      0,
      0,
      0,
      0,
      0,
      0,
      0,
      0,
      0,
      0,
      0,
      0,
      0,
      0,
      0,
      0,
      0,
      0,
      0,
      0,
      0,
      0,
      0,
      0,
      0,
      0,
      0,
      0,
      0,
      0,
      0,
      0,
      0,
      0,
      0,
      0,
      0,
      0,
      0,
      0,
      0,
      0,
      0,
      0,
      0,
      0,
      0,
      0,
      0,
      0,
      0,
      0,
      0,
      0,
      0,
      0,
      0,
      0,
      0,
      0,
      0,
      0,
      0,
      0,
      0,
      0,
      0,
      0,
      0,
      0,
      0,
      0,
      0,
      0,
      0,
      0,
      0,
      0,
      0,
      0,
      0,
      0,
      0,
      0,
      0,
      0,
      0,
      0,
      0,
      0,
      0,
      0,
      0,
      0,
      0,
      0,
      0,
      0,
      0,
      0,
      0,
      0,
      0,
      0,
      0,
      0,
      0,
      0,
      0,
      0,
      0,
      0,
      0,
      0,
      0,
      0,
      0,
      0,
      0,
      0,
      0,
      0,
      0,
      0,
      0,
      0,
      0,
      0,
      0,
      0,
      0,
      0,
      0,
      0,
      0,
      0,
      0,
      0,
      0,
      0,
      0,
      0,
      0,
      0,
      0,
      0,
      0,
      0,
      0,
      0,
      0,
      0,
      0,
      0,
      0,
      0,
      0,
      0,
      0,
      0,
      0,
      0,
      0,
      0,
      0,
      0,
      0,
      0,
      0,
      0,
      0,
      0,
      0,
      0,
      0,
      0,
      0,
      0,
      0,
      0,
      0,
      0,
      0,
      0,
      0,
      0,
      0,
      0,
      0,
      0,
      0,
      0,
      0,
      0,
      0,
      0,
      0,
      0,
      0,
      0,
      0,
      0,
      0,
      0,
      0,
      0,
      0,
      0,
      0,
      0,
      0,
      0,
      0,
      0,
      0,
      0,
      0,
      0,
      0,
      0,
      0,
      0,
      0,
      0,
      0,
      0,
      0,
      0,
      0,
      0,
      0,
      0,
      0,
      0,
      0,
      0,
      0,
      0,
      0,
      0,
      0,
      0,
      0,
      0,
      0,
      0,
      0,
      0,
      0,
      0,
      0,
      0,
      0,
      0,
      0,
      0,
      0,
      0,
      0,
      0,
      0,
      0,
      0,
      0,
      0,
      0,
      0,
      0,
      0,
      0,
      0,
      0,
      0,
      0,
      0,
      0,
      0,
      0,
      0,
      0,
      0,
      0,
      0,
      0,
      0,
      0,
      0,
      0,
      0,
      0,
      0,
      0,
      0,
      0,
      0,
      0,
      0,
      0,
      0,
      0,
      0,
      0,
      0,
      0,
      0,
      0,
      0,
      0,
      0,
      0,
      0,
      0,
      0,
      0,
      0,
      0,
      0,
      0,
      0,
      0,
      0,
      0,
      0,
      0,
      0,
      0,
      0,
      0,
      0,
      0,
      0,
      0,
      0,
      0,
      0,
      0,
      0,
      0,
      0,
      0,
      0,
      0,
      0,
      0,
      0,
      0,
      0,
      0,
      0,
      0,
      0,
      0,
      0,
      0,
      0,
      0,
      0,
      0,
      0,
      0,
      0,
      0,
      0,
      0,
      0,
      0,
      0,
      0,
      0,
      0,
      0,
      0,
      0,
      0,
      0,
      0,
      0,
      0,
      0,
      0,
      0,
      0,
      0,
      0,
      0,
      0,
      0,
      0,
      0,
      0,
      0,
      0,
      0,
      0,
      0,
      0,
      0,
      0,
      0,
      0,
      0,
      0,
      0,
      0,
      0,
      0,
      0,
      0,
      0,
      0,
      0,
      0,
      0,
      0,
      0,
      0,
      0,
      0,
      0,
      0,
      0,
      0,
      0,
      0,
      0,
      0,
      0,
      0,
      0,
      0,
      0,
      0,
      0,
      0,
      0,
      0,
      0,
      0,
      0,
      0,
      0,
      0,
      0,
      0,
      0,
      0,
      0,
      0,
      0,
      0,
      0,
      0,
      0,
      0,
      0,
      0,
      0,
      0,
      0,
      0,
      0,
      0,
      0,
      0,
      0,
      0,
      0,
      0,
      0,
      0,
      0,
      0,
      0,
      0,
      0,
      0,
      0,
      0,
      0,
      0,
      0,
      0,
      0,
      0,
      0,
      0,
      0,
      0,
      0,
      0,
      0,
      0,
      0,
      0,
      0,
      0,
      0,
      0,
      0,
      0,
      0,
      0,
      0,
      0,
      0,
      0,
      0,
      0,
      0,
      0,
      0,
      0,
      0,
      0,
      0,
      0,
      0,
      0,
      0,
      0,
      0,
      0,
      0,
      0,
      0,
      0,
      0,
      0,
      0,
      0,
      0,
      0,
      0,
      0,
      0,
      0,
      0,
      0,
      0,
      0,
      0,
      0,
      0,
      0,
      0,
      0,
      0,
      0,
      0,
      0,
      0,
      0,
      0,
      0,
      0,
      0,
      0,
      0,
      0,
      0,
      0,
      0,
      0,
      0,
      0,
      0,
      0,
      0,
      0,
      0,
      0,
      0,
      0,
      0,
      0,
      0,
      0,
      0,
      0,
      0,
      0,
      0,
      0,
      0,
      0,
      0,
      0,
      0,
      0,
      0,
      0,
      0,
      0,
      0,
      0,
      0,
      0,
      0,
      0,
      0,
      0,
      0,
      0,
      0,
      0,
      0,
      0,
      0,
      0,
      0,
      0,
      0,
      0,
      0,
      0,
      0,
      0,
      0,
      0,
      0,
      0,
      0,
      0,
      0,
      0,
      0,
      0,
      0,
      0,
      0,
      0,
      0,
      0,
      0,
      0,
      0,
      0,
      0,
      0,
      0,
      0,
      0,
      0,
      0,
      0,
      0,
      0,
      0,
      0,
      0,
      0,
      0,
      0,
      0,
      0,
      0,
      0,
      0,
      0,
      0,
      0,
      0,
      0,
      0,
      0,
      0,
      0,
      0,
      0,
      0,
      0,
      0,
      0,
      0,
      0,
      0,
      0,
      0,
      0,
      0,
      0,
      0,
      0,
      0,
      0,
      0,
      0,
      0,
      0,
      0,
      0,
      0,
      0,
      0,
      0,
      0,
      0,
      0,
      0,
      0,
      0,
      0,
      0,
      0,
      0,
      0,
      0,
      0,
      0,
      0,
      0,
      0,
      0,
      0,
      0,
      0,
      0,
      0,
      0,
      0,
      0,
      0,
      0,
      0,
      0,
      0,
      0,
      0,
      0,
      0,
      0,
      0,
      0,
      0,
      0,
      0,
      0,
      0,
      0,
      0,
      0,
      0,
      0,
      0,
      0,
      0,
      0,
      0,
      0,
      0,
      0,
      0,
      0,
      0,
      0,
      0,
      0,
      0,
      0,
      0,
      0,
      0,
      0,
      0,
      0,
      0,
      0,
      0,
      0,
      0,
      0,
      0,
      0,
      0,
      0,
      0,
      0,
      0,
      0,
      0,
      0,
      0,
      0,
      0,
      0,
      0,
      0,
      0,
      0,
      0,
      0,
      0,
      0,
      0,
      0,
      0,
      0,
      0,
      0,
      0,
      0,
      0,
      0,
      0,
      0,
      0,
      0,
      0,
      0,
      0,
      0,
      0,
      0,
      0,
      0,
      0,
      0,
      0,
      0,
      0,
      0,
      0,
      0,
      0,
      0,
      0,
      0,
      0,
      0,
      0,
      0,
      0,
      0,
      0,
      0,
      0,
      0,
      0,
      0,
      0,
      0,
      0,
      0,
      0,
      0,
      0,
      0,
      0,
      0,
      0,
      0,
      0,
      0,
      0,
      0,
      0,
      0,
      0,
      0,
      0,
      0,
      0,
      0,
      0,
      0,
      0,
      0,
      0,
      0,
      0,
      0,
      0,
      0,
      0,
      0,
      0,
      0,
      0,
      0,
      0,
      0,
      0,
      0,
      0,
      0,
      0,
      0,
      0,
      0,
      0,
      0,
      0,
      0,
      0,
      0,
      0,
      0,
      0,
      0,
      0,
      0,
      0,
      0,
      0,
      0,
      0,
      0,
      0,
      0,
      0,
      0,
      0,
      0,
      0,
      0,
      0,
      0,
      0,
      0,
      0,
      0,
      0,
      0,
      0,
      0,
      0,
      0,
      0,
      0,
      0,
      0,
      0,
      0,
      0,
      0,
      0,
      0,
      0,
      0,
      0,
      0,
      0,
      0,
      0,
      0,
      0,
      0,
      0,
      0,
      0,
      0,
      0,
      0,
      0,
      0,
      0,
      0,
      0,
      0,
      0,
      0,
      0,
      0,
      0,
      0,
      0,
      0,
      0,
      0,
      0,
      0,
      0,
      0,
      0,
      0,
      0,
      0,
      0,
      0,
      0,
      0,
      0,
      0,
      0,
      0,
      0,
      0,
      0,
      0,
      0,
      0,
      0,
      0,
      0,
      0,
      0,
      0,
      0,
      0,
      0,
      0,
      0,
      0,
      0,
      0,
      0,
      0,
      0,
      0,
      0,
      0,
      0,
      0,
      0,
      0,
      0,
      0,
      0,
      0,
      0,
      0,
      0,
      0,
      0,
      0,
      0,
      0,
      0,
      0,
      0,
      0,
      0,
      0,
      0,
      0,
      0,
      0,
      0,
      0,
      0,
      0,
      0,
      0,
      0,
      0,
      0,
      0,
      0,
      0,
      0,
      0,
      0,
      0,
      0,
      0,
      0,
      0,
      0,
      0,
      0,
      0,
      0,
      0,
      0,
      0,
      0,
      0,
      0,
      0,
      0,
      0,
      0,
      0,
      0,
      0,
      0,
      0,
      0,
      0,
      0,
      0,
      0,
      0,
      0,
      0,
      0,
      0,
      0,
      0,
      0,
      0,
      0,
      0,
      0,
      0,
      0,
      0,
      0,
      0,
      0,
      0,
      0,
      0,
      0,
      0,
      0,
      0,
      0,
      0,
      0,
      0,
      0,
      0,
      0,
      0,
      0,
      0,
      0,
      0,
      0,
      0,
      0,
      0,
      0,
      0,
      0,
      0,
      0,
      0,
      0,
      0,
      0,
      0,
      0,
      0,
      0,
      0,
      0,
      0,
      0,
      0,
      0,
      0,
      0,
      0,
      0,
      0,
      0,
      0,
      0,
      0,
      0,
      0,
      0,
      0,
      0,
      0,
      0,
      0,
      0,
      0,
      0,
      0,
      0,
      0,
      0,
      0,
      0,
      0,
      0,
      0,
      0,
      0,
      0,
      0,
      0,
      0,
      0,
      0,
      0,
      0,
      0,
      0,
      0,
      0,
      0,
      0,
      0,
      0,
      0,
      0,
      0,
      0,
      0,
      0,
      0,
      0,
      0,
      0,
      0,
      0,
      0,
      0,
      0,
      0,
      0,
      0,
      0,
      0,
      0,
      0,
      0,
      0
    ]
  }
}